README.rst
setup.py
UtilsCell/__init__.py
UtilsCell/emailutils.py
UtilsCell/osutils.py
UtilsCell/spiderutils.py
UtilsCell/sshutils.py
UtilsCell/tenminutesemail.py
UtilsCell.egg-info/PKG-INFO
UtilsCell.egg-info/SOURCES.txt
UtilsCell.egg-info/dependency_links.txt
UtilsCell.egg-info/requires.txt
UtilsCell.egg-info/top_level.txt
UtilsCell.egg-info/zip-safe
UtilsCell/tools/__init__.py
UtilsCell/tools/redirect_log.py