Metadata-Version: 1.1
Name: UtilsCell
Version: 0.0.5
Summary: 一些常用工具
Home-page: https://github.com/SunJackson/myutils
Author: JacksonSun
Author-email: 306862600@qq.com
License: MIT
Keywords: Utils email ssh
Platform: UNKNOWN
Classifier: License :: OSI Approved :: MIT License
Classifier: Programming Language :: Python
Classifier: Intended Audience :: Developers
Classifier: Operating System :: OS Independent
